lft/__init__.py
lft/main.py
linux_forensic_toolkit-1.0.1.dist-info/LICENSE
linux_forensic_toolkit-1.0.1.dist-info/METADATA
linux_forensic_toolkit-1.0.1.dist-info/WHEEL
linux_forensic_toolkit-1.0.1.dist-info/entry_points.txt
linux_forensic_toolkit-1.0.1.dist-info/top_level.txt
linux_forensic_toolkit-1.0.1.dist-info/RECORD
