Metadata-Version: 2.1
Name: linux-forensic-toolkit
Version: 1.0.1
Summary: Linux Forensic Analysis Toolkit
Home-page: https://github.com/Veyselxan/linux-forensic-toolkit
Author: veyselxan
Author-email: info@veyse-xan.com
License: UNKNOWN
Platform: UNKNOWN
Classifier: Programming Language :: Python :: 3
Classifier: License :: OSI Approved :: MIT License
Classifier: Operating System :: POSIX :: Linux
Requires-Python: >=3.6
Requires-Dist: prettytable (>=3.0.0)
Requires-Dist: psutil (>=5.8.0)
